citier/__init__.py
citier/cities.py
citier/city.py
citier/country.py
citier/data.py
citier/state.py
citier-1.4.5.dist-info/METADATA
citier-1.4.5.dist-info/WHEEL
citier-1.4.5.dist-info/top_level.txt
citier-1.4.5.dist-info/RECORD
